softcopy/__init__.py
softcopy/copier.py
softcopy/hcs_copier.py
softcopy/main.py
softcopy/packed_name.py
softcopy/priority.py
softcopy/slow_write.py
softcopy/to_ome.py
softcopy/zarr_copier.py
softcopy/zarr_utils.py
softcopy-0.0.12.dist-info/licenses/LICENSE
softcopy-0.0.12.dist-info/METADATA
softcopy-0.0.12.dist-info/WHEEL
softcopy-0.0.12.dist-info/entry_points.txt
softcopy-0.0.12.dist-info/top_level.txt
softcopy-0.0.12.dist-info/RECORD
