Metadata-Version: 2.4
Name: softcopy
Version: 0.0.12
Summary: Copies zarr archives from an acquisition frontend to a different disk, using filesystem watching and lockfiles to allow copying during acquisition.
Author-email: Seth Hinz <sethhinz@me.com>
Project-URL: Homepage, https://royerlab.github.io/softcopy/
Project-URL: Repository, https://github.com/royerlab/softcopy
Project-URL: Documentation, https://royerlab.github.io/softcopy/
Keywords: python
Requires-Python: >=3.11
License-File: LICENSE
Requires-Dist: numpy==2.1.1
Requires-Dist: watchdog>=5.0.3
Requires-Dist: psutil>=6.0.0
Requires-Dist: click>=8.1.7
Requires-Dist: pyyaml>=6.0.2
Requires-Dist: iohub>=0.2.0
Dynamic: license-file
